mammos_dft/__init__.py
mammos_dft/db.py
mammos_dft/py.typed
mammos_dft/_ai/__init__.py
mammos_dft/_rspt/__init__.py
mammos_dft/data/db.csv
mammos_dft/data/0001/exchange
mammos_dft/data/0001/momfile
mammos_dft/data/0001/posfile
mammos_dft/data/0001/structure.cif
mammos_dft/data/0002/exchange
mammos_dft/data/0002/momfile
mammos_dft/data/0002/posfile
mammos_dft/data/0002/structure.cif
mammos_dft/data/0005/exchange
mammos_dft/data/0005/momfile
mammos_dft/data/0005/posfile
mammos_dft/data/0005/structure.cif
mammos_dft/data/0006/exchange
mammos_dft/data/0006/momfile
mammos_dft/data/0006/posfile
mammos_dft/data/0006/structure.cif
mammos_dft/data/0007/exchange
mammos_dft/data/0007/momfile
mammos_dft/data/0007/posfile
mammos_dft/data/0007/structure.cif
mammos_dft-0.4.0.dist-info/METADATA
mammos_dft-0.4.0.dist-info/WHEEL
mammos_dft-0.4.0.dist-info/licenses/LICENSE
mammos_dft-0.4.0.dist-info/RECORD
