Metadata-Version: 2.4
Name: mammos-dft
Version: 0.4.0
Summary: Density functional theory (DFT) methods package for ab-initio calculations.
Project-URL: Homepage, https://mammos-project.github.io
Project-URL: Documentation, https://mammos-project.github.io/mammos
Project-URL: Repository, https://github.com/MaMMoS-project/mammos-dft
Project-URL: Issues, https://github.com/MaMMoS-project/mammos-dft/issues
Project-URL: Changelog, https://mammos-project.github.io/mammos/changelog
Author: Andrea Petrocchi, Swapneel Amit Pathak, Martin Lang, Sam Holt, Hans Fangohr
License-Expression: MIT
License-File: LICENSE
Classifier: Intended Audience :: Developers
Classifier: Intended Audience :: Education
Classifier: Intended Audience :: Science/Research
Classifier: Programming Language :: Python :: 3 :: Only
Classifier: Topic :: Scientific/Engineering :: Physics
Requires-Python: >=3.11
Requires-Dist: ase
Requires-Dist: mammos-entity>=0.8.0
Requires-Dist: mammos-units
Requires-Dist: pandas
Requires-Dist: pydantic
Requires-Dist: rich
